<?xml version="1.0" encoding="utf-8" ?><dwsync><file name="jquery.sliderPro.js" server="45.33.119.94" local="3603894526" remote="321982814042919166" Dst="-1" /><file name="jquery.sliderProCustomThumbnails.js" server="45.33.119.94" local="3603894526" remote="321982814042919166" Dst="-1" /><file name="leanner-modal.js" server="45.33.119.94" local="3603894526" remote="321982814042919166" Dst="-1" /><file name="hoverintent.js" server="45.33.119.94" local="3603894526" remote="321982814042919166" Dst="-1" /><file name="Tocca.min.js" server="45.33.119.94" local="3603894526" remote="321982814042919166" Dst="-1" /><file name="jquery.wpexEqualHeights.js" server="45.33.119.94" local="3603894526" remote="321982814042919166" Dst="-1" /><file name="scrolly.js" server="45.33.119.94" local="3603894526" remote="321982814042919166" Dst="-1" /><file name="typed.js" server="45.33.119.94" local="3603894526" remote="321982814042919166" Dst="-1" /><file name="appear.js" server="45.33.119.94" local="3603894526" remote="321982814042919166" Dst="-1" /><file name="ilightbox.js" server="45.33.119.94" local="3603894526" remote="321982814042919166" Dst="-1" /><file name="tipsy.js" server="45.33.119.94" local="3603894526" remote="321982814042919166" Dst="-1" /><file name="images-loaded.js" server="45.33.119.94" local="3603894526" remote="321982814042919166" Dst="-1" /><file name="touch-swipe.js" server="45.33.119.94" local="3603894526" remote="321982814042919166" Dst="-1" /><file name="jquery.mousewheel.js" server="45.33.119.94" local="3603894526" remote="321982814042919166" Dst="-1" /><file name="sidr.js" server="45.33.119.94" local="3603894526" remote="321982814042919166" Dst="-1" /><file name="isotope.js" server="45.33.119.94" local="3603894526" remote="321982814042919166" Dst="-1" /><file name="wpex.owl.carousel.js" server="45.33.119.94" local="3603894526" remote="321982814042919166" Dst="-1" /><file name="supersubs.js" server="45.33.119.94" local="3603894526" remote="321982814042919166" Dst="-1" /><file name="superfish.js" server="45.33.119.94" local="3603894526" remote="321982814042919166" Dst="-1" /><file name="countUp-jquery.js" server="45.33.119.94" local="3603894526" remote="321982814042919166" Dst="-1" /><file name="jquery.easing.js" server="45.33.119.94" local="3603894526" remote="321982814042919166" Dst="-1" /></dwsync>