<?xml version="1.0" encoding="utf-8" ?><dwsync><file name="portfolio-single-meta.php" server="45.33.119.94" local="3603894526" remote="321982814042919166" Dst="-1" /><file name="portfolio-entry-title.php" server="45.33.119.94" local="3603894526" remote="321982814042919166" Dst="-1" /><file name="portfolio-entry-excerpt.php" server="45.33.119.94" local="3603894526" remote="321982814042919166" Dst="-1" /><file name="portfolio-single-title.php" server="45.33.119.94" local="3603894526" remote="321982814042919166" Dst="-1" /><file name="portfolio-single-media.php" server="45.33.119.94" local="3603894526" remote="321982814042919166" Dst="-1" /><file name="portfolio-single-related.php" server="45.33.119.94" local="3603894526" remote="321982814042919166" Dst="-1" /><file name="portfolio-entry-content.php" server="45.33.119.94" local="3603894526" remote="321982814042919166" Dst="-1" /><file name="portfolio-entry.php" server="45.33.119.94" local="3603894526" remote="321982814042919166" Dst="-1" /><file name="portfolio-single-share.php" server="45.33.119.94" local="3603894526" remote="321982814042919166" Dst="-1" /><file name="portfolio-single-layout.php" server="45.33.119.94" local="3603894526" remote="321982814042919166" Dst="-1" /><file name="portfolio-single-gallery.php" server="45.33.119.94" local="3603894526" remote="321982814042919166" Dst="-1" /><file name="portfolio-entry-media.php" server="45.33.119.94" local="3603894526" remote="321982814042919166" Dst="-1" /><file name="portfolio-single-content.php" server="45.33.119.94" local="3603894526" remote="321982814042919166" Dst="-1" /><file name="portfolio-single-comments.php" server="45.33.119.94" local="3603894526" remote="321982814042919166" Dst="-1" /></dwsync>